LICENSE
README.md
pyproject.toml
setup.py
meeteval/__init__.py
meeteval/_typing.py
meeteval.egg-info/PKG-INFO
meeteval.egg-info/SOURCES.txt
meeteval.egg-info/dependency_links.txt
meeteval.egg-info/entry_points.txt
meeteval.egg-info/requires.txt
meeteval.egg-info/top_level.txt
meeteval/der/__init__.py
meeteval/der/__main__.py
meeteval/der/api.py
meeteval/der/md_eval.py
meeteval/der/nryant_dscore.py
meeteval/io/__init__.py
meeteval/io/__main__.py
meeteval/io/base.py
meeteval/io/chime7.py
meeteval/io/ctm.py
meeteval/io/keyed_text.py
meeteval/io/pbjson.py
meeteval/io/py.py
meeteval/io/rttm.py
meeteval/io/seglst.py
meeteval/io/smart.py
meeteval/io/stm.py
meeteval/io/uem.py
meeteval/viz/__init__.py
meeteval/viz/__main__.py
meeteval/viz/file_server.py
meeteval/viz/overview_table.html
meeteval/viz/overview_table.py
meeteval/viz/side_by_side_sync.html
meeteval/viz/visualize.css
meeteval/viz/visualize.js
meeteval/viz/visualize.py
meeteval/wer/__init__.py
meeteval/wer/__main__.py
meeteval/wer/api.py
meeteval/wer/normalizer.py
meeteval/wer/preprocess.py
meeteval/wer/utils.py
meeteval/wer/matching/__init__.py
meeteval/wer/matching/cy_greedy_combination_matching.cpp
meeteval/wer/matching/cy_greedy_combination_matching.pyx
meeteval/wer/matching/cy_levenshtein.cpp
meeteval/wer/matching/cy_levenshtein.pyx
meeteval/wer/matching/cy_mimo_matching.cpp
meeteval/wer/matching/cy_mimo_matching.pyx
meeteval/wer/matching/cy_orc_matching.cpp
meeteval/wer/matching/cy_orc_matching.pyx
meeteval/wer/matching/cy_time_constrained_mimo_matching.cpp
meeteval/wer/matching/cy_time_constrained_mimo_matching.pyx
meeteval/wer/matching/cy_time_constrained_orc_matching.cpp
meeteval/wer/matching/cy_time_constrained_orc_matching.pyx
meeteval/wer/matching/greedy_combination_matching.py
meeteval/wer/matching/levenshtein.h
meeteval/wer/matching/mimo_matching.h
meeteval/wer/matching/mimo_matching.py
meeteval/wer/matching/orc_matching.py
meeteval/wer/matching/time_constrained_mimo_matching.h
meeteval/wer/matching/time_constrained_orc_matching.h
meeteval/wer/wer/__init__.py
meeteval/wer/wer/cp.py
meeteval/wer/wer/di_cp.py
meeteval/wer/wer/error_rate.py
meeteval/wer/wer/mimo.py
meeteval/wer/wer/orc.py
