Metadata-Version: 2.4
Name: meeteval
Version: 0.4.3
Home-page: https://github.com/fgnt/meeteval/
Author: Department of Communications Engineering, Paderborn University
Author-email: sek@nt.upb.de
License: MIT
Keywords: speech recognition,word error rate,evaluation,meeting,ASR,WER
Classifier: Development Status :: 5 - Production/Stable
Classifier: Intended Audience :: Science/Research
Classifier: License :: OSI Approved :: MIT License
Classifier: Programming Language :: Python :: 3.8
Classifier: Programming Language :: Python :: 3.9
Classifier: Programming Language :: Python :: 3.10
Classifier: Programming Language :: Python :: 3.11
Classifier: Programming Language :: Python :: 3.12
Requires-Python: >=3.5
License-File: LICENSE
Requires-Dist: kaldialign
Requires-Dist: numpy
Requires-Dist: scipy
Requires-Dist: typing_extensions; python_version < "3.8"
Requires-Dist: cached_property; python_version < "3.8"
Requires-Dist: Cython
Requires-Dist: packaging
Provides-Extra: cli
Requires-Dist: pyyaml; extra == "cli"
Requires-Dist: fire; extra == "cli"
Requires-Dist: simplejson; extra == "cli"
Requires-Dist: aiohttp; extra == "cli"
Requires-Dist: soundfile; extra == "cli"
Requires-Dist: tqdm; extra == "cli"
Requires-Dist: yattag; extra == "cli"
Requires-Dist: platformdirs; extra == "cli"
Provides-Extra: test
Requires-Dist: editdistance; extra == "test"
Requires-Dist: pytest; extra == "test"
Requires-Dist: hypothesis; extra == "test"
Requires-Dist: coverage; extra == "test"
Requires-Dist: pytest-cov; extra == "test"
Requires-Dist: paderbox; extra == "test"
Requires-Dist: pyyaml; extra == "test"
Requires-Dist: fire; extra == "test"
Requires-Dist: simplejson; extra == "test"
Requires-Dist: aiohttp; extra == "test"
Requires-Dist: soundfile; extra == "test"
Requires-Dist: tqdm; extra == "test"
Requires-Dist: yattag; extra == "test"
Requires-Dist: platformdirs; extra == "test"
Provides-Extra: all
Requires-Dist: lazy_dataset; extra == "all"
Requires-Dist: ipywidgets; extra == "all"
Requires-Dist: pyyaml; extra == "all"
Requires-Dist: fire; extra == "all"
Requires-Dist: simplejson; extra == "all"
Requires-Dist: aiohttp; extra == "all"
Requires-Dist: soundfile; extra == "all"
Requires-Dist: tqdm; extra == "all"
Requires-Dist: yattag; extra == "all"
Requires-Dist: platformdirs; extra == "all"
Requires-Dist: editdistance; extra == "all"
Requires-Dist: pytest; extra == "all"
Requires-Dist: hypothesis; extra == "all"
Requires-Dist: coverage; extra == "all"
Requires-Dist: pytest-cov; extra == "all"
Requires-Dist: paderbox; extra == "all"
Dynamic: author
Dynamic: author-email
Dynamic: classifier
Dynamic: description
Dynamic: description-content-type
Dynamic: home-page
Dynamic: keywords
Dynamic: license
Dynamic: license-file
Dynamic: provides-extra
Dynamic: requires-dist
Dynamic: requires-python
